rst/CNKI_API.py
rst/Google_Scholar_API.py
rst/__init__.py
rst/occurences.py
rst/rst.py
research_scraping_tool-0.0.2.dist-info/LICENSE
research_scraping_tool-0.0.2.dist-info/METADATA
research_scraping_tool-0.0.2.dist-info/WHEEL
research_scraping_tool-0.0.2.dist-info/entry_points.txt
research_scraping_tool-0.0.2.dist-info/top_level.txt
research_scraping_tool-0.0.2.dist-info/RECORD
