Metadata-Version: 2.1
Name: research-scraping-tool
Version: 0.0.2
Summary: A tool to scrape research in academic databases like Google Scholar
License: GNU General Public License v3.0
Keywords: scraper,google scholar,CNKI,research
Classifier: Development Status :: 2 - Pre-Alpha
Classifier: Intended Audience :: Science/Research
Classifier: License :: OSI Approved :: GNU General Public License v3 (GPLv3)
Classifier: Natural Language :: English
Classifier: Operating System :: OS Independent
Classifier: Topic :: Scientific/Engineering :: Information Analysis
Classifier: Programming Language :: Python :: 3
License-File: LICENSE
Requires-Dist: requests
Requires-Dist: beautifulsoup4
Requires-Dist: selenium
Requires-Dist: fake-useragent
Requires-Dist: pathlib
Requires-Dist: importlib-metadata ; python_version < "3.8"
